pyais/__init__.py
pyais/ais_decode.py
pyais/ais_encode.py
pyais/ais_types.py
pyais/constants.py
pyais/decode.py
pyais/encode.py
pyais/exceptions.py
pyais/filter.py
pyais/messages.py
pyais/py.typed
pyais/queue.py
pyais/stream.py
pyais/tracker.py
pyais/util.py
pyais-2.13.3.dist-info/licenses/LICENSE
pyais-2.13.3.dist-info/METADATA
pyais-2.13.3.dist-info/WHEEL
pyais-2.13.3.dist-info/entry_points.txt
pyais-2.13.3.dist-info/top_level.txt
pyais-2.13.3.dist-info/RECORD
