Metadata-Version: 2.4
Name: pyais
Version: 2.13.3
Summary: AIS message decoding
Author-email: Leon Morten Richter <misc@leonmortenrichter.de>
Maintainer-email: Leon Morten Richter <misc@leonmortenrichter.de>
License: MIT License
Project-URL: Homepage, https://github.com/M0r13n/pyais
Project-URL: Source, https://github.com/M0r13n/pyais
Keywords: AIS,ship,decoding,NMEA,maritime
Classifier: Development Status :: 5 - Production/Stable
Classifier: Intended Audience :: Developers
Classifier: License :: OSI Approved :: MIT License
Classifier: Operating System :: OS Independent
Classifier: Programming Language :: Python :: 3
Classifier: Programming Language :: Python :: 3.9
Classifier: Programming Language :: Python :: 3.10
Classifier: Programming Language :: Python :: 3.11
Classifier: Programming Language :: Python :: 3.12
Classifier: Programming Language :: Python :: 3.13
Classifier: Programming Language :: Python :: 3 :: Only
Classifier: Topic :: Communications
Classifier: Topic :: System :: Networking
Classifier: Typing :: Typed
Requires-Python: >=3.9
License-File: LICENSE
Requires-Dist: bitarray
Requires-Dist: attrs
Provides-Extra: dev
Requires-Dist: mypy; extra == "dev"
Requires-Dist: flake8; extra == "dev"
Requires-Dist: coverage; extra == "dev"
Requires-Dist: twine; extra == "dev"
Requires-Dist: sphinx; extra == "dev"
Requires-Dist: pytest; extra == "dev"
Requires-Dist: pytest-cov; extra == "dev"
Dynamic: license-file
